talkylabs/__init__.py
talkylabs/reach/__init__.py
talkylabs/reach/request_validator.py
talkylabs/reach/base/__init__.py
talkylabs/reach/base/client_base.py
talkylabs/reach/base/deserialize.py
talkylabs/reach/base/domain.py
talkylabs/reach/base/exceptions.py
talkylabs/reach/base/instance_context.py
talkylabs/reach/base/instance_resource.py
talkylabs/reach/base/list_resource.py
talkylabs/reach/base/obsolete.py
talkylabs/reach/base/page.py
talkylabs/reach/base/serialize.py
talkylabs/reach/base/values.py
talkylabs/reach/base/version.py
talkylabs/reach/http/__init__.py
talkylabs/reach/http/async_http_client.py
talkylabs/reach/http/http_client.py
talkylabs/reach/http/request.py
talkylabs/reach/http/response.py
talkylabs/reach/rest/__init__.py
talkylabs/reach/rest/api/ApiBase.py
talkylabs/reach/rest/api/__init__.py
talkylabs/reach/rest/api/authentix/__init__.py
talkylabs/reach/rest/api/authentix/authentication_trial_item.py
talkylabs/reach/rest/api/authentix/authentication_trial_stat_item.py
talkylabs/reach/rest/api/authentix/configuration_item/__init__.py
talkylabs/reach/rest/api/authentix/configuration_item/authentication_control_item.py
talkylabs/reach/rest/api/authentix/configuration_item/authentication_item.py
talkylabs/reach/rest/api/messaging/__init__.py
talkylabs/reach/rest/api/messaging/messaging_item.py
reach_talkylabs-1.0.0.dist-info/AUTHORS.md
reach_talkylabs-1.0.0.dist-info/LICENSE
reach_talkylabs-1.0.0.dist-info/METADATA
reach_talkylabs-1.0.0.dist-info/WHEEL
reach_talkylabs-1.0.0.dist-info/top_level.txt
reach_talkylabs-1.0.0.dist-info/RECORD
