Metadata-Version: 2.1
Name: reach-talkylabs
Version: 1.0.0
Summary: Reach@Talkylabs API client
Home-page: https://github.com/talkylabs/reach-python/
Author: Talkylabs
Author-email: help@talkylabs.com
Keywords: reach-talkylabs
Classifier: Development Status :: 5 - Production/Stable
Classifier: Intended Audience :: Developers
Classifier: License :: OSI Approved :: MIT License
Classifier: Operating System :: OS Independent
Classifier: Programming Language :: Python
Classifier: Programming Language :: Python :: 3.7
Classifier: Programming Language :: Python :: 3.8
Classifier: Programming Language :: Python :: 3.9
Classifier: Programming Language :: Python :: 3.10
Classifier: Programming Language :: Python :: 3.11
Classifier: Programming Language :: Python :: Implementation :: CPython
Classifier: Topic :: Software Development :: Libraries :: Python Modules
Classifier: Topic :: Communications :: Telephony
Requires-Python: >=3.7.0
License-File: LICENSE
License-File: AUTHORS.md
Requires-Dist: pytz
Requires-Dist: requests >=2.0.0
Requires-Dist: PyJWT <3.0.0,>=2.0.0
Requires-Dist: aiohttp >=3.8.4
Requires-Dist: aiohttp-retry >=2.8.3
